YouTubeEased/__init__.py
YouTubeEased/utils.py
YouTubeEased-1.0.4.dist-info/Licence.txt
YouTubeEased-1.0.4.dist-info/METADATA
YouTubeEased-1.0.4.dist-info/WHEEL
YouTubeEased-1.0.4.dist-info/top_level.txt
YouTubeEased-1.0.4.dist-info/RECORD
