Metadata-Version: 2.1
Name: YouTubeEased
Version: 1.0.4
Summary: A basic library which will give you a better and easier experience with youtube API
Home-page: UNKNOWN
Author: Daniel Katz
Author-email: 
License: MIT
Platform: UNKNOWN
Classifier: License :: OSI Approved :: MIT License
Classifier: Programming Language :: Python :: 3
Classifier: Operating System :: Microsoft :: Windows
Requires-Dist: YouTubeEased
